pyeodhistoricaldata/__init__.py
pyeodhistoricaldata/api.py
pyeodhistoricaldata-0.0.3.dist-info/LICENSE
pyeodhistoricaldata-0.0.3.dist-info/METADATA
pyeodhistoricaldata-0.0.3.dist-info/WHEEL
pyeodhistoricaldata-0.0.3.dist-info/top_level.txt
pyeodhistoricaldata-0.0.3.dist-info/RECORD
